ffeat/NormalizedPipe.py
ffeat/Pipe.py
ffeat/__init__.py
ffeat/_common/AlgorithmSkeleton.py
ffeat/_common/Evaluation.py
ffeat/_common/__init__.py
ffeat/_common/crossover/OnePoint1D.py
ffeat/_common/crossover/TwoPoint1D.py
ffeat/_common/crossover/Uniform.py
ffeat/_common/crossover/_Shared.py
ffeat/_common/crossover/__init__.py
ffeat/_common/initialization/Uniform.py
ffeat/_common/initialization/__init__.py
ffeat/_common/selection/Elitism.py
ffeat/_common/selection/Roulette.py
ffeat/_common/selection/StochasticUniversalSampling.py
ffeat/_common/selection/Tournament.py
ffeat/_common/selection/__init__.py
ffeat/cma/CMAESBasic.py
ffeat/cma/CMAESRankU.py
ffeat/cma/CMAESRankU_negative_weights.py
ffeat/cma/CMAES_as_pseudocode.py
ffeat/cma/__init__.py
ffeat/flow/Concat.py
ffeat/flow/EachArg.py
ffeat/flow/Lambda.py
ffeat/flow/Parallel.py
ffeat/flow/Repeat.py
ffeat/flow/Replace.py
ffeat/flow/Select.py
ffeat/flow/Sequence.py
ffeat/flow/__init__.py
ffeat/genetic/Initialization.py
ffeat/genetic/__init__.py
ffeat/genetic/crossover/__init__.py
ffeat/genetic/mutation/FlipBit.py
ffeat/genetic/mutation/__init__.py
ffeat/genetic/selection/__init__.py
ffeat/measure/Base.py
ffeat/measure/FitnessMean.py
ffeat/measure/FitnessQuantile.py
ffeat/measure/FitnessStd.py
ffeat/measure/__init__.py
ffeat/measure/fitness_highest_lowest.py
ffeat/measure/reporting/Array.py
ffeat/measure/reporting/Console.py
ffeat/measure/reporting/File.py
ffeat/measure/reporting/__init__.py
ffeat/pso/Initialization.py
ffeat/pso/PSO.py
ffeat/pso/__init__.py
ffeat/pso/_private/UpdateGlobalBest.py
ffeat/pso/_private/UpdateLocalBest.py
ffeat/pso/_private/UpdatePosition.py
ffeat/pso/_private/__init__.py
ffeat/pso/clip/Position.py
ffeat/pso/clip/Velocity.py
ffeat/pso/clip/__init__.py
ffeat/pso/neighborhood/Grid.py
ffeat/pso/neighborhood/Nearest.py
ffeat/pso/neighborhood/Neighborhood.py
ffeat/pso/neighborhood/Random.py
ffeat/pso/neighborhood/Static.py
ffeat/pso/neighborhood/__init__.py
ffeat/pso/update/PSO2006.py
FFEAT-1.0.0.dist-info/LICENSE.md
FFEAT-1.0.0.dist-info/METADATA
FFEAT-1.0.0.dist-info/WHEEL
FFEAT-1.0.0.dist-info/top_level.txt
FFEAT-1.0.0.dist-info/RECORD
