Metadata-Version: 2.1
Name: FFEAT
Version: 1.0.0
Summary: Framework for Evolutionary Algorithms in Torch
Home-page: https://github.com/PatrikValkovic/FEAT
Author: Patrik Valkovic
License: GNU LGPLv3
Download-URL: https://github.com/PatrikValkovic/FEAT/archive/v1.0.0.tar.gz
Platform: UNKNOWN
Requires-Dist: torch
Requires-Dist: numpy
